singleton/__init__.py
singleton/admin.py
singleton/apps.py
singleton/models.py
singleton/tests.py
singleton/views.py
singleton/migrations/__init__.py
django_newsingleton-1.1.dist-info/LICENSE
django_newsingleton-1.1.dist-info/METADATA
django_newsingleton-1.1.dist-info/WHEEL
django_newsingleton-1.1.dist-info/top_level.txt
django_newsingleton-1.1.dist-info/RECORD
