Metadata-Version: 2.1
Name: django-newsingleton
Version: 1.1
Summary: A simple class Singleton for create models like 'dynamic settings'
Author-email: pavelbeard <heavycream9090@icloud.com>
Project-URL: Homepage, https://github.com/pavelbeard/django-newsingleton
Project-URL: Issues, https://github.com/pavelbeard/django-newsingleton/issues
Classifier: Programming Language :: Python :: 3
Classifier: License :: OSI Approved :: MIT License
Classifier: Operating System :: OS Independent
Requires-Python: >=3.8
License-File: LICENSE
